Workbook

Sheet Home
A1: APARTMENT MANAGEMENT SYSTEM
A2: Property Operations & Financial Tracking
A4: Welcome to the Apartment Management System
A5: Manage apartments, tenants, rent payments, maintenance, expenses, and property performance from one centralized Excel workbook.
B8: DASHBOARD | N8: APARTMENTS
B9: Executive Property Overview | N9: Unit & Occupancy Management
B10: View key property, financial, occupancy, and maintenance performance. | N10: View apartment details, rent rates, and occupancy status.
B12: TENANTS | N12: RENT PAYMENTS
B13: Tenant & Lease Records | N13: Rent Collection Tracking
B14: Manage tenant information, leases, and assigned apartments. | N14: Monitor payments, outstanding balances, and payment timing.
B16: MAINTENANCE | N16: EXPENSES
B17: Maintenance Management | N17: Operating Expense Tracking
B18: Track service requests, priorities, costs, and completion status. | N18: Review property expenses by category, building, and vendor
H20: ANALYSIS
H21: Property Performance Analysis
H22: Review financial, occupancy, rent, and maintenance performance.

Sheet Apartments
A1: Apartment_ID | B1: Building | C1: Floor | D1: Unit_Number | E1: Apartment_Type | F1: Bedrooms | G1: Monthly_Rent | H1: Occupancy_Status
A2: A001 | B2: Building A | C2: 1 | D2: 101 | E2: Studio | F2: 0 | G2: 1800 | H2: Occupied
A3: A002 | B3: Building A | C3: 1 | D3: 102 | E3: 1 Bedroom | F3: 1 | G3: 2300 | H3: Occupied
A4: A003 | B4: Building A | C4: 1 | D4: 103 | E4: 2 Bedroom | F4: 2 | G4: 3100 | H4: Vacant
A5: A004 | B5: Building A | C5: 2 | D5: 201 | E5: 1 Bedroom | F5: 1 | G5: 2400 | H5: Occupied
A6: A005 | B6: Building A | C6: 2 | D6: 202 | E6: 2 Bedroom | F6: 2 | G6: 3200 | H6: Occupied
A7: A006 | B7: Building A | C7: 2 | D7: 203 | E7: Studio | F7: 0 | G7: 1900 | H7: Occupied
A8: A007 | B8: Building A | C8: 3 | D8: 301 | E8: 3 Bedroom | F8: 3 | G8: 4100 | H8: Occupied
A9: A008 | B9: Building A | C9: 3 | D9: 302 | E9: 2 Bedroom | F9: 2 | G9: 2600 | H9: Vacant
A10: A009 | B10: Building A | C10: 3 | D10: 303 | E10: Studio | F10: 0 | G10: 1500 | H10: Vacant
A11: B001 | B11: Building B | C11: 1 | D11: 101 | E11: Studio | F11: 0 | G11: 1750 | H11: Occupied
A12: B002 | B12: Building B | C12: 1 | D12: 102 | E12: 1 Bedroom | F12: 1 | G12: 2250 | H12: Occupied
A13: B003 | B13: Building B | C13: 1 | D13: 103 | E13: 2 Bedroom | F13: 2 | G13: 3000 | H13: Occupied
... A17: B007 | B17: Building B | C17: 3 | D17: 302 | E17: 1 Bedroom | F17: 1 | G17: 2500 | H17: Occupied

Sheet Tenants
A1: Tenant_ID | B1: First_Name | C1: Last_Name | D1: Phone | E1: Email | F1: Apartment_ID | G1: Lease_Start | H1: Lease_End | I1: Monthly_Rent | J1: Tenant_Status
A2: T001 | B2: Omar | C2: Hassan | D2: 551234101 | E2: omar.hassan@example.com | F2: A001 | G2: 46023 | H2: 46387 | I2: =_xlfn.XLOOKUP(Table2[[#This Row],[Apartment_ID]],Table1[Apartment_ID],Table1[Monthly_Rent],"") -> 1800 | J2: Active
A3: T002 | B3: Lina | C3: Ahmed | D3: 551234102 | E3: lina.ahmed@example.com | F3: A002 | G3: 46082 | H3: 46446 | I3: =_xlfn.XLOOKUP(Table2[[#This Row],[Apartment_ID]],Table1[Apartment_ID],Table1[Monthly_Rent],"") -> 2300 | J3: Active
A4: T003 | B4: Youssef | C4: Ali | D4: 551234103 | E4: youssef.ali@example.com | F4: A004 | G4: 46068 | H4: 46432 | I4: =_xlfn.XLOOKUP(Table2[[#This Row],[Apartment_ID]],Table1[Apartment_ID],Table1[Monthly_Rent],"") -> 2400 | J4: Active
A5: T004 | B5: Mariam | C5: Khalid | D5: 551234104 | E5: mariam.khalid@example.com | F5: A005 | G5: 46174 | H5: 46538 | I5: =_xlfn.XLOOKUP(Table2[[#This Row],[Apartment_ID]],Table1[Apartment_ID],Table1[Monthly_Rent],"") -> 3200 | J5: Active
A6: T005 | B6: Adam | C6: Ibrahim | D6: 551234105 | E6: adam.ibrahim@example.com | F6: A006 | G6: 46113 | H6: 46477 | I6: =_xlfn.XLOOKUP(Table2[[#This Row],[Apartment_ID]],Table1[Apartment_ID],Table1[Monthly_Rent],"") -> 1900 | J6: Active
A7: T006 | B7: Sara | C7: Mahmoud | D7: 551234106 | E7: sara.mahmoud@example.com | F7: A007 | G7: 45901 | H7: 46265 | I7: =_xlfn.XLOOKUP(Table2[[#This Row],[Apartment_ID]],Table1[Apartment_ID],Table1[Monthly_Rent],"") -> 4100 | J7: Active
A8: T007 | B8: Noor | C8: Saleh | D8: 551234107 | E8: noor.saleh@example.com | F8: B001 | G8: 46054 | H8: 46418 | I8: =_xlfn.XLOOKUP(Table2[[#This Row],[Apartment_ID]],Table1[Apartment_ID],Table1[Monthly_Rent],"") -> 1750 | J8: Active
A9: T008 | B9: Zain | C9: Abdullah | D9: 551234108 | E9: zain.abdullah@example.com | F9: B002 | G9: 46143 | H9: 46507 | I9: =_xlfn.XLOOKUP(Table2[[#This Row],[Apartment_ID]],Table1[Apartment_ID],Table1[Monthly_Rent],"") -> 2250 | J9: Active
A10: T009 | B10: Huda | C10: Nasser | D10: 551234109 | E10: huda.nasser@example.com | F10: B003 | G10: 46204 | H10: 46568 | I10: =_xlfn.XLOOKUP(Table2[[#This Row],[Apartment_ID]],Table1[Apartment_ID],Table1[Monthly_Rent],"") -> 3000 | J10: Active
A11: T010 | B11: Faisal | C11: Hamad | D11: 551234110 | E11: faisal.hamad@example.com | F11: B005 | G11: 46023 | H11: 46387 | I11: =_xlfn.XLOOKUP(Table2[[#This Row],[Apartment_ID]],Table1[Apartment_ID],Table1[Monthly_Rent],"") -> 3150 | J11: Active
A12: T011 | B12: Reem | C12: Saad | D12: 551234111 | E12: reem.saad@example.com | F12: B006 | G12: 45931 | H12: 46295 | I12: =_xlfn.XLOOKUP(Table2[[#This Row],[Apartment_ID]],Table1[Apartment_ID],Table1[Monthly_Rent],"") -> 4000 | J12: Active
A13: T012 | B13: Layla | C13: Mustafa | D13: 551234112 | E13: layla.mustafa@example.com | F13: B007 | G13: 46235 | H13: 46599 | I13: =_xlfn.XLOOKUP(Table2[[#This Row],[Apartment_ID]],Table1[Apartment_ID],Table1[Monthly_Rent],"") -> 2500 | J13: Active

Sheet Rent_Payments
I1: Rent Due Date(Month) | J1: 5
A4: Payment_ID | B4: Tenant_ID | C4: Apartment_ID | D4: Payment_Month | E4: Due_Amount | F4: Paid_Amount | G4: Balance | H4: Payment_Date | I4: Payment_Method | J4: Payment_Status | K4: Payment_Timing
A5: P001 | B5: T001 | C5: =_xlfn.XLOOKUP(Table3[[#This Row],[Tenant_ID]],Table2[Tenant_ID],Table2[Apartment_ID],"") -> A001 | D5: 46204 | E5: =_xlfn.XLOOKUP(Table3[[#This Row],[Tenant_ID]],Table2[Tenant_ID],Table2[Monthly_Rent],"") -> 1800 | F5: 1800 | G5: =MAX(Table3[[#This Row],[Due_Amount]]-Table3[[#This Row],[Paid_Amount]],0) -> 0 | H5: 46206 | I5: Bank Transfer | J5: =IF(Table3[[#This Row],[Paid_Amount]]=0,"Unpaid",IF(Table3[[#This Row],[Paid_Amount]]<Table3[[#This Row],[Due_Amount]],"Partial","Paid")) -> Paid | K5: =IF(Table3[[#This Row],[Paid_Amount]]=0,"Not Paid",IF(DAY(Table3[[#This Row],[Payment_Date]])<=$J$1,"On-time","Late")) -> On-time
A6: P002 | B6: T002 | C6: =_xlfn.XLOOKUP(Table3[[#This Row],[Tenant_ID]],Table2[Tenant_ID],Table2[Apartment_ID],"") -> A002 | D6: 46204 | E6: =_xlfn.XLOOKUP(Table3[[#This Row],[Tenant_ID]],Table2[Tenant_ID],Table2[Monthly_Rent],"") -> 2300 | F6: 2300 | G6: =MAX(Table3[[#This Row],[Due_Amount]]-Table3[[#This Row],[Paid_Amount]],0) -> 0 | H6: 46205 | I6: Bank Transfer | J6: =IF(Table3[[#This Row],[Paid_Amount]]=0,"Unpaid",IF(Table3[[#This Row],[Paid_Amount]]<Table3[[#This Row],[Due_Amount]],"Partial","Paid")) -> Paid | K6: =IF(Table3[[#This Row],[Paid_Amount]]=0,"Not Paid",IF(DAY(Table3[[#This Row],[Payment_Date]])<=$J$1,"On-time","Late")) -> On-time
A7: P003 | B7: T003 | C7: =_xlfn.XLOOKUP(Table3[[#This Row],[Tenant_ID]],Table2[Tenant_ID],Table2[Apartment_ID],"") -> A004 | D7: 46204 | E7: =_xlfn.XLOOKUP(Table3[[#This Row],[Tenant_ID]],Table2[Tenant_ID],Table2[Monthly_Rent],"") -> 2400 | F7: 2400 | G7: =MAX(Table3[[#This Row],[Due_Amount]]-Table3[[#This Row],[Paid_Amount]],0) -> 0 | H7: 46210 | I7: Cash | J7: =IF(Table3[[#This Row],[Paid_Amount]]=0,"Unpaid",IF(Table3[[#This Row],[Paid_Amount]]<Table3[[#This Row],[Due_Amount]],"Partial","Paid")) -> Paid | K7: =IF(Table3[[#This Row],[Paid_Amount]]=0,"Not Paid",IF(DAY(Table3[[#This Row],[Payment_Date]])<=$J$1,"On-time","Late")) -> Late
A8: P004 | B8: T004 | C8: =_xlfn.XLOOKUP(Table3[[#This Row],[Tenant_ID]],Table2[Tenant_ID],Table2[Apartment_ID],"") -> A005 | D8: 46204 | E8: =_xlfn.XLOOKUP(Table3[[#This Row],[Tenant_ID]],Table2[Tenant_ID],Table2[Monthly_Rent],"") -> 3200 | F8: 3200 | G8: =MAX(Table3[[#This Row],[Due_Amount]]-Table3[[#This Row],[Paid_Amount]],0) -> 0 | H8: 46208 | I8: Card | J8: =IF(Table3[[#This Row],[Paid_Amount]]=0,"Unpaid",IF(Table3[[#This Row],[Paid_Amount]]<Table3[[#This Row],[Due_Amount]],"Partial","Paid")) -> Paid | K8: =IF(Table3[[#This Row],[Paid_Amount]]=0,"Not Paid",IF(DAY(Table3[[#This Row],[Payment_Date]])<=$J$1,"On-time","Late")) -> On-time
A9: P005 | B9: T005 | C9: =_xlfn.XLOOKUP(Table3[[#This Row],[Tenant_ID]],Table2[Tenant_ID],Table2[Apartment_ID],"") -> A006 | D9: 46204 | E9: =_xlfn.XLOOKUP(Table3[[#This Row],[Tenant_ID]],Table2[Tenant_ID],Table2[Monthly_Rent],"") -> 1900 | F9: 1900 | G9: =MAX(Table3[[#This Row],[Due_Amount]]-Table3[[#This Row],[Paid_Amount]],0) -> 0 | H9: 46215 | I9: Bank Transfer | J9: =IF(Table3[[#This Row],[Paid_Amount]]=0,"Unpaid",IF(Table3[[#This Row],[Paid_Amount]]<Table3[[#This Row],[Due_Amount]],"Partial","Paid")) -> Paid | K9: =IF(Table3[[#This Row],[Paid_Amount]]=0,"Not Paid",IF(DAY(Table3[[#This Row],[Payment_Date]])<=$J$1,"On-time","Late")) -> Late
A10: P006 | B10: T006 | C10: =_xlfn.XLOOKUP(Table3[[#This Row],[Tenant_ID]],Table2[Tenant_ID],Table2[Apartment_ID],"") -> A007 | D10: 46204 | E10: =_xlfn.XLOOKUP(Table3[[#This Row],[Tenant_ID]],Table2[Tenant_ID],Table2[Monthly_Rent],"") -> 4100 | F10: 4100 | G10: =MAX(Table3[[#This Row],[Due_Amount]]-Table3[[#This Row],[Paid_Amount]],0) -> 0 | H10: 46204 | I10: Bank Transfer | J10: =IF(Table3[[#This Row],[Paid_Amount]]=0,"Unpaid",IF(Table3[[#This Row],[Paid_Amount]]<Table3[[#This Row],[Due_Amount]],"Partial","Paid")) -> Paid | K10: =IF(Table3[[#This Row],[Paid_Amount]]=0,"Not Paid",IF(DAY(Table3[[#This Row],[Payment_Date]])<=$J$1,"On-time","Late")) -> On-time
A11: P007 | B11: T007 | C11: =_xlfn.XLOOKUP(Table3[[#This Row],[Tenant_ID]],Table2[Tenant_ID],Table2[Apartment_ID],"") -> B001 | D11: 46204 | E11: =_xlfn.XLOOKUP(Table3[[#This Row],[Tenant_ID]],Table2[Tenant_ID],Table2[Monthly_Rent],"") -> 1750 | F11: 1750 | G11: =MAX(Table3[[#This Row],[Due_Amount]]-Table3[[#This Row],[Paid_Amount]],0) -> 0 | H11: 46206 | I11: Cash | J11: =IF(Table3[[#This Row],[Paid_Amount]]=0,"Unpaid",IF(Table3[[#This Row],[Paid_Amount]]<Table3[[#This Row],[Due_Amount]],"Partial","Paid")) -> Paid | K11: =IF(Table3[[#This Row],[Paid_Amount]]=0,"Not Paid",IF(DAY(Table3[[#This Row],[Payment_Date]])<=$J$1,"On-time","Late")) -> On-time
A12: P008 | B12: T008 | C12: =_xlfn.XLOOKUP(Table3[[#This Row],[Tenant_ID]],Table2[Tenant_ID],Table2[Apartment_ID],"") -> B002 | D12: 46204 | E12: =_xlfn.XLOOKUP(Table3[[#This Row],[Tenant_ID]],Table2[Tenant_ID],Table2[Monthly_Rent],"") -> 2250 | F12: 2250 | G12: =MAX(Table3[[#This Row],[Due_Amount]]-Table3[[#This Row],[Paid_Amount]],0) -> 0 | H12: 46209 | I12: Card | J12: =IF(Table3[[#This Row],[Paid_Amount]]=0,"Unpaid",IF(Table3[[#This Row],[Paid_Amount]]<Table3[[#This Row],[Due_Amount]],"Partial","Paid")) -> Paid | K12: =IF(Table3[[#This Row],[Paid_Amount]]=0,"Not Paid",IF(DAY(Table3[[#This Row],[Payment_Date]])<=$J$1,"On-time","Late")) -> Late
A13: P009 | B13: T009 | C13: =_xlfn.XLOOKUP(Table3[[#This Row],[Tenant_ID]],Table2[Tenant_ID],Table2[Apartment_ID],"") -> B003 | D13: 46204 | E13: =_xlfn.XLOOKUP(Table3[[#This Row],[Tenant_ID]],Table2[Tenant_ID],Table2[Monthly_Rent],"") -> 3000 | F13: 3000 | G13: =MAX(Table3[[#This Row],[Due_Amount]]-Table3[[#This Row],[Paid_Amount]],0) -> 0 | H13: 46207 | I13: Bank Transfer | J13: =IF(Table3[[#This Row],[Paid_Amount]]=0,"Unpaid",IF(Table3[[#This Row],[Paid_Amount]]<Table3[[#This Row],[Due_Amount]],"Partial","Paid")) -> Paid | K13: =IF(Table3[[#This Row],[Paid_Amount]]=0,"Not Paid",IF(DAY(Table3[[#This Row],[Payment_Date]])<=$J$1,"On-time","Late")) -> On-time
A14: P010 | B14: T010 | C14: =_xlfn.XLOOKUP(Table3[[#This Row],[Tenant_ID]],Table2[Tenant_ID],Table2[Apartment_ID],"") -> B005 | D14: 46204 | E14: =_xlfn.XLOOKUP(Table3[[#This Row],[Tenant_ID]],Table2[Tenant_ID],Table2[Monthly_Rent],"") -> 3150 | F14: 2500 | G14: =MAX(Table3[[#This Row],[Due_Amount]]-Table3[[#This Row],[Paid_Amount]],0) -> 650 | H14: 46218 | I14: Cash | J14: =IF(Table3[[#This Row],[Paid_Amount]]=0,"Unpaid",IF(Table3[[#This Row],[Paid_Amount]]<Table3[[#This Row],[Due_Amount]],"Partial","Paid")) -> Partial | K14: =IF(Table3[[#This Row],[Paid_Amount]]=0,"Not Paid",IF(DAY(Table3[[#This Row],[Payment_Date]])<=$J$1,"On-time","Late")) -> Late
A15: P011 | B15: T011 | C15: =_xlfn.XLOOKUP(Table3[[#This Row],[Tenant_ID]],Table2[Tenant_ID],Table2[Apartment_ID],"") -> B006 | D15: 46204 | E15: =_xlfn.XLOOKUP(Table3[[#This Row],[Tenant_ID]],Table2[Tenant_ID],Table2[Monthly_Rent],"") -> 4000 | F15: 4000 | G15: =MAX(Table3[[#This Row],[Due_Amount]]-Table3[[#This Row],[Paid_Amount]],0) -> 0 | H15: 46205 | I15: Bank Transfer | J15: =IF(Table3[[#This Row],[Paid_Amount]]=0,"Unpaid",IF(Table3[[#This Row],[Paid_Amount]]<Table3[[#This Row],[Due_Amount]],"Partial","Paid")) -> Paid | K15: =IF(Table3[[#This Row],[Paid_Amount]]=0,"Not Paid",IF(DAY(Table3[[#This Row],[Payment_Date]])<=$J$1,"On-time","Late")) -> On-time
A16: P012 | B16: T012 | C16: =_xlfn.XLOOKUP(Table3[[#This Row],[Tenant_ID]],Table2[Tenant_ID],Table2[Apartment_ID],"") -> B007 | D16: 46235 | E16: =_xlfn.XLOOKUP(Table3[[#This Row],[Tenant_ID]],Table2[Tenant_ID],Table2[Monthly_Rent],"") -> 2500 | F16: 2500 | G16: =MAX(Table3[[#This Row],[Due_Amount]]-Table3[[#This Row],[Paid_Amount]],0) -> 0 | H16: 46237 | I16: Card | J16: =IF(Table3[[#This Row],[Paid_Amount]]=0,"Unpaid",IF(Table3[[#This Row],[Paid_Amount]]<Table3[[#This Row],[Due_Amount]],"Partial","Paid")) -> Paid | K16: =IF(Table3[[#This Row],[Paid_Amount]]=0,"Not Paid",IF(DAY(Table3[[#This Row],[Payment_Date]])<=$J$1,"On-time","Late")) -> On-time
... A27: P023 | B27: T011 | C27: =_xlfn.XLOOKUP(Table3[[#This Row],[Tenant_ID]],Table2[Tenant_ID],Table2[Apartment_ID],"") -> B006 | D27: 46235 | E27: =_xlfn.XLOOKUP(Table3[[#This Row],[Tenant_ID]],Table2[Tenant_ID],Table2[Monthly_Rent],"") -> 4000 | F27: 3500 | G27: =MAX(Table3[[#This Row],[Due_Amount]]-Table3[[#This Row],[Paid_Amount]],0) -> 500 | H27: 46254 | I27: Bank Transfer | J27: =IF(Table3[[#This Row],[Paid_Amount]]=0,"Unpaid",IF(Table3[[#This Row],[Paid_Amount]]<Table3[[#This Row],[Due_Amount]],"Partial","Paid")) -> Partial | K27: =IF(Table3[[#This Row],[Paid_Amount]]=0,"Not Paid",IF(DAY(Table3[[#This Row],[Payment_Date]])<=$J$1,"On-time","Late")) -> Late

Sheet Maintenance
A1: Request_ID | B1: Apartment_ID | C1: Request_Date | D1: Category | E1: Description | F1: Priority | G1: Maintenance_Status | H1: Completion_Date | I1: Cost | J1: Vendor | K1: Days_Open | L1: Attention_Flag
A2: M001 | B2: A001 | C2: 46178 | D2: Plumbing | E2: Kitchen sink leakage | F2: Medium | G2: Completed | H2: 46179 | I2: 180 | J2: Al Noor Maintenance | K2: =IF(Table4[[#This Row],[Maintenance_Status]]="Completed",Table4[[#This Row],[Completion_Date]]-Table4[[#This Row],[Request_Date]],TODAY()-Table4[[#This Row],[Request_Date]]) -> 1 | L2: =IF(Table4[[#This Row],[Maintenance_Status]]="Completed","Closed",IF(AND(Table4[[#This Row],[Priority]]="High",Table4[[#This Row],[Maintenance_Status]]<>"Completed"),"Urgent",IF(Table4[[#This Row],[Days_Open]]>14,"Needs Attention","Normal"))) -> Closed
A3: M002 | B3: A004 | C3: 46185 | D3: Electrical | E3: Bedroom light issue | F3: Low | G3: Completed | H3: 46185 | I3: 90 | J3: BrightFix Services | K3: =IF(Table4[[#This Row],[Maintenance_Status]]="Completed",Table4[[#This Row],[Completion_Date]]-Table4[[#This Row],[Request_Date]],TODAY()-Table4[[#This Row],[Request_Date]]) -> 0 | L3: =IF(Table4[[#This Row],[Maintenance_Status]]="Completed","Closed",IF(AND(Table4[[#This Row],[Priority]]="High",Table4[[#This Row],[Maintenance_Status]]<>"Completed"),"Urgent",IF(Table4[[#This Row],[Days_Open]]>14,"Needs Attention","Normal"))) -> Closed
A4: M003 | B4: A005 | C4: 46191 | D4: AC | E4: AC not cooling properly | F4: High | G4: Completed | H4: 46193 | I4: 450 | J4: CoolAir Services | K4: =IF(Table4[[#This Row],[Maintenance_Status]]="Completed",Table4[[#This Row],[Completion_Date]]-Table4[[#This Row],[Request_Date]],TODAY()-Table4[[#This Row],[Request_Date]]) -> 2 | L4: =IF(Table4[[#This Row],[Maintenance_Status]]="Completed","Closed",IF(AND(Table4[[#This Row],[Priority]]="High",Table4[[#This Row],[Maintenance_Status]]<>"Completed"),"Urgent",IF(Table4[[#This Row],[Days_Open]]>14,"Needs Attention","Normal"))) -> Closed
A5: M004 | B5: A007 | C5: 46198 | D5: Plumbing | E5: Bathroom pipe leakage | F5: High | G5: Completed | H5: 46199 | I5: 320 | J5: Al Noor Maintenance | K5: =IF(Table4[[#This Row],[Maintenance_Status]]="Completed",Table4[[#This Row],[Completion_Date]]-Table4[[#This Row],[Request_Date]],TODAY()-Table4[[#This Row],[Request_Date]]) -> 1 | L5: =IF(Table4[[#This Row],[Maintenance_Status]]="Completed","Closed",IF(AND(Table4[[#This Row],[Priority]]="High",Table4[[#This Row],[Maintenance_Status]]<>"Completed"),"Urgent",IF(Table4[[#This Row],[Days_Open]]>14,"Needs Attention","Normal"))) -> Closed
A6: M005 | B6: B001 | C6: 46206 | D6: Electrical | E6: Power outlet damaged | F6: Medium | G6: Completed | H6: 46207 | I6: 120 | J6: BrightFix Services | K6: =IF(Table4[[#This Row],[Maintenance_Status]]="Completed",Table4[[#This Row],[Completion_Date]]-Table4[[#This Row],[Request_Date]],TODAY()-Table4[[#This Row],[Request_Date]]) -> 1 | L6: =IF(Table4[[#This Row],[Maintenance_Status]]="Completed","Closed",IF(AND(Table4[[#This Row],[Priority]]="High",Table4[[#This Row],[Maintenance_Status]]<>"Completed"),"Urgent",IF(Table4[[#This Row],[Days_Open]]>14,"Needs Attention","Normal"))) -> Closed
A7: M006 | B7: B003 | C7: 46212 | D7: Appliance | E7: Refrigerator repair | F7: Medium | G7: Completed | H7: 46214 | I7: 350 | J7: HomeTech Repairs | K7: =IF(Table4[[#This Row],[Maintenance_Status]]="Completed",Table4[[#This Row],[Completion_Date]]-Table4[[#This Row],[Request_Date]],TODAY()-Table4[[#This Row],[Request_Date]]) -> 2 | L7: =IF(Table4[[#This Row],[Maintenance_Status]]="Completed","Closed",IF(AND(Table4[[#This Row],[Priority]]="High",Table4[[#This Row],[Maintenance_Status]]<>"Completed"),"Urgent",IF(Table4[[#This Row],[Days_Open]]>14,"Needs Attention","Normal"))) -> Closed
A8: M007 | B8: A002 | C8: 46218 | D8: AC | E8: AC filter replacement | F8: Low | G8: Completed | H8: 46218 | I8: 100 | J8: CoolAir Services | K8: =IF(Table4[[#This Row],[Maintenance_Status]]="Completed",Table4[[#This Row],[Completion_Date]]-Table4[[#This Row],[Request_Date]],TODAY()-Table4[[#This Row],[Request_Date]]) -> 0 | L8: =IF(Table4[[#This Row],[Maintenance_Status]]="Completed","Closed",IF(AND(Table4[[#This Row],[Priority]]="High",Table4[[#This Row],[Maintenance_Status]]<>"Completed"),"Urgent",IF(Table4[[#This Row],[Days_Open]]>14,"Needs Attention","Normal"))) -> Closed
A9: M008 | B9: B006 | C9: 46225 | D9: Plumbing | E9: Low water pressure | F9: Medium | G9: Completed | H9: 46227 | I9: 220 | J9: Al Noor Maintenance | K9: =IF(Table4[[#This Row],[Maintenance_Status]]="Completed",Table4[[#This Row],[Completion_Date]]-Table4[[#This Row],[Request_Date]],TODAY()-Table4[[#This Row],[Request_Date]]) -> 2 | L9: =IF(Table4[[#This Row],[Maintenance_Status]]="Completed","Closed",IF(AND(Table4[[#This Row],[Priority]]="High",Table4[[#This Row],[Maintenance_Status]]<>"Completed"),"Urgent",IF(Table4[[#This Row],[Days_Open]]>14,"Needs Attention","Normal"))) -> Closed
A10: M009 | B10: A006 | C10: 46235 | D10: Electrical | E10: Ceiling light failure | F10: Low | G10: Completed | H10: 46236 | I10: 80 | J10: BrightFix Services | K10: =IF(Table4[[#This Row],[Maintenance_Status]]="Completed",Table4[[#This Row],[Completion_Date]]-Table4[[#This Row],[Request_Date]],TODAY()-Table4[[#This Row],[Request_Date]]) -> 1 | L10: =IF(Table4[[#This Row],[Maintenance_Status]]="Completed","Closed",IF(AND(Table4[[#This Row],[Priority]]="High",Table4[[#This Row],[Maintenance_Status]]<>"Completed"),"Urgent",IF(Table4[[#This Row],[Days_Open]]>14,"Needs Attention","Normal"))) -> Closed
A11: M010 | B11: B005 | C11: 46238 | D11: AC | E11: AC water leakage | F11: High | G11: In Progress | I11: 275 | J11: CoolAir Services | K11: =IF(Table4[[#This Row],[Maintenance_Status]]="Completed",Table4[[#This Row],[Completion_Date]]-Table4[[#This Row],[Request_Date]],TODAY()-Table4[[#This Row],[Request_Date]]) -> 34 | L11: =IF(Table4[[#This Row],[Maintenance_Status]]="Completed","Closed",IF(AND(Table4[[#This Row],[Priority]]="High",Table4[[#This Row],[Maintenance_Status]]<>"Completed"),"Urgent",IF(Table4[[#This Row],[Days_Open]]>14,"Needs Attention","Normal"))) -> Urgent
A12: M011 | B12: A007 | C12: 46242 | D12: Appliance | E12: Washing machine issue | F12: Medium | G12: Pending | I12: 0 | K12: =IF(Table4[[#This Row],[Maintenance_Status]]="Completed",Table4[[#This Row],[Completion_Date]]-Table4[[#This Row],[Request_Date]],TODAY()-Table4[[#This Row],[Request_Date]]) -> 30 | L12: =IF(Table4[[#This Row],[Maintenance_Status]]="Completed","Closed",IF(AND(Table4[[#This Row],[Priority]]="High",Table4[[#This Row],[Maintenance_Status]]<>"Completed"),"Urgent",IF(Table4[[#This Row],[Days_Open]]>14,"Needs Attention","Normal"))) -> Needs Attention
A13: M012 | B13: B002 | C13: 46245 | D13: Plumbing | E13: Shower drain blocked | F13: Medium | G13: Completed | H13: 46246 | I13: 140 | J13: Al Noor Maintenance | K13: =IF(Table4[[#This Row],[Maintenance_Status]]="Completed",Table4[[#This Row],[Completion_Date]]-Table4[[#This Row],[Request_Date]],TODAY()-Table4[[#This Row],[Request_Date]]) -> 1 | L13: =IF(Table4[[#This Row],[Maintenance_Status]]="Completed","Closed",IF(AND(Table4[[#This Row],[Priority]]="High",Table4[[#This Row],[Maintenance_Status]]<>"Completed"),"Urgent",IF(Table4[[#This Row],[Days_Open]]>14,"Needs Attention","Normal"))) -> Closed
A14: M013 | B14: A003 | C14: 46248 | D14: Painting | E14: Repaint vacant apartment | F14: Low | G14: In Progress | I14: 650 | J14: FreshCo Paints | K14: =IF(Table4[[#This Row],[Maintenance_Status]]="Completed",Table4[[#This Row],[Completion_Date]]-Table4[[#This Row],[Request_Date]],TODAY()-Table4[[#This Row],[Request_Date]]) -> 24 | L14: =IF(Table4[[#This Row],[Maintenance_Status]]="Completed","Closed",IF(AND(Table4[[#This Row],[Priority]]="High",Table4[[#This Row],[Maintenance_Status]]<>"Completed"),"Urgent",IF(Table4[[#This Row],[Days_Open]]>14,"Needs Attention","Normal"))) -> Needs Attention
A15: M014 | B15: B004 | C15: 46253 | D15: Cleaning | E15: Deep cleaning before rental | F15: Low | G15: Completed | H15: 46254 | I15: 200 | J15: Sparkle Cleaning | K15: =IF(Table4[[#This Row],[Maintenance_Status]]="Completed",Table4[[#This Row],[Completion_Date]]-Table4[[#This Row],[Request_Date]],TODAY()-Table4[[#This Row],[Request_Date]]) -> 1 | L15: =IF(Table4[[#This Row],[Maintenance_Status]]="Completed","Closed",IF(AND(Table4[[#This Row],[Priority]]="High",Table4[[#This Row],[Maintenance_Status]]<>"Completed"),"Urgent",IF(Table4[[#This Row],[Days_Open]]>14,"Needs Attention","Normal"))) -> Closed
A16: M015 | B16: A008 | C16: 46257 | D16: Electrical | E16: Replace damaged switches | F16: Medium | G16: Pending | I16: 0 | K16: =IF(Table4[[#This Row],[Maintenance_Status]]="Completed",Table4[[#This Row],[Completion_Date]]-Table4[[#This Row],[Request_Date]],TODAY()-Table4[[#This Row],[Request_Date]]) -> 15 | L16: =IF(Table4[[#This Row],[Maintenance_Status]]="Completed","Closed",IF(AND(Table4[[#This Row],[Priority]]="High",Table4[[#This Row],[Maintenance_Status]]<>"Completed"),"Urgent",IF(Table4[[#This Row],[Days_Open]]>14,"Needs Attention","Normal"))) -> Needs Attention
A17: M016 | B17: B007 | C17: 46260 | D17: Plumbing | E17: Toilet flush issue | F17: Medium | G17: In Progress | I17: 160 | J17: Al Noor Maintenance | K17: =IF(Table4[[#This Row],[Maintenance_Status]]="Completed",Table4[[#This Row],[Completion_Date]]-Table4[[#This Row],[Request_Date]],TODAY()-Table4[[#This Row],[Request_Date]]) -> 12 | L17: =IF(Table4[[#This Row],[Maintenance_Status]]="Completed","Closed",IF(AND(Table4[[#This Row],[Priority]]="High",Table4[[#This Row],[Maintenance_Status]]<>"Completed"),"Urgent",IF(Table4[[#This Row],[Days_Open]]>14,"Needs Attention","Normal"))) -> Normal
A18: M017 | B18: A005 | C18: 46261 | D18: AC | E18: Routine AC maintenance | F18: Low | G18: Completed | H18: 46262 | I18: 120 | J18: CoolAir Services | K18: =IF(Table4[[#This Row],[Maintenance_Status]]="Completed",Table4[[#This Row],[Completion_Date]]-Table4[[#This Row],[Request_Date]],TODAY()-Table4[[#This Row],[Request_Date]]) -> 1 | L18: =IF(Table4[[#This Row],[Maintenance_Status]]="Completed","Closed",IF(AND(Table4[[#This Row],[Priority]]="High",Table4[[#This Row],[Maintenance_Status]]<>"Completed"),"Urgent",IF(Table4[[#This Row],[Days_Open]]>14,"Needs Attention","Normal"))) -> Closed
A19: M018 | B19: B003 | C19: 46263 | D19: Appliance | E19: Oven heating issue | F19: Medium | G19: Pending | I19: 0 | J19: HomeTech Repairs | K19: =IF(Table4[[#This Row],[Maintenance_Status]]="Completed",Table4[[#This Row],[Completion_Date]]-Table4[[#This Row],[Request_Date]],TODAY()-Table4[[#This Row],[Request_Date]]) -> 9 | L19: =IF(Table4[[#This Row],[Maintenance_Status]]="Completed","Closed",IF(AND(Table4[[#This Row],[Priority]]="High",Table4[[#This Row],[Maintenance_Status]]<>"Completed"),"Urgent",IF(Table4[[#This Row],[Days_Open]]>14,"Needs Attention","Normal"))) -> Normal

Sheet Expenses
A1: Expense_ID | B1: Expense_Date | C1: Expense_Category | D1: Description | E1: Building | F1: Amount | G1: Payment_Method | H1: Vendor
A2: E001 | B2: 46174 | C2: Utilities | D2: Building A electricity | E2: Building A | F2: 1250 | G2: Bank Transfer | H2: Utility Company
A3: E002 | B3: 46174 | C3: Utilities | D3: Building B electricity | E3: Building B | F3: 1120 | G3: Bank Transfer | H3: Utility Company
A4: E003 | B4: 46178 | C4: Cleaning | D4: Common area cleaning | E4: Building A | F4: 450 | G4: Bank Transfer | H4: Sparkle Cleaning
A5: E004 | B5: 46178 | C5: Cleaning | D5: Common area cleaning | E5: Building B | F5: 420 | G5: Bank Transfer | H5: Sparkle Cleaning
A6: E005 | B6: 46183 | C6: Security | D6: Monthly security service | E6: Both | F6: 1500 | G6: Bank Transfer | H6: SafeGuard Security
A7: E006 | B7: 46188 | C7: Internet | D7: Building internet service | E7: Both | F7: 600 | G7: Card | H7: ConnectNet
A8: E007 | B8: 46204 | C8: Utilities | D8: Building A electricity | E8: Building A | F8: 1380 | G8: Bank Transfer | H8: Utility Company
A9: E008 | B9: 46204 | C9: Utilities | D9: Building B electricity | E9: Building B | F9: 1210 | G9: Bank Transfer | H9: Utility Company
A10: E009 | B10: 46208 | C10: Cleaning | D10: Common area cleaning | E10: Building A | F10: 450 | G10: Bank Transfer | H10: Sparkle Cleaning
A11: E010 | B11: 46208 | C11: Cleaning | D11: Common area cleaning | E11: Building B | F11: 420 | G11: Bank Transfer | H11: Sparkle Cleaning
A12: E011 | B12: 46213 | C12: Security | D12: Monthly security service | E12: Both | F12: 1500 | G12: Bank Transfer | H12: SafeGuard Security
A13: E012 | B13: 46218 | C13: Internet | D13: Building internet service | E13: Both | F13: 600 | G13: Card | H13: ConnectNet
... A25: E024 | B25: 46263 | C25: Pest Control | D25: Routine pest control | E25: Both | F25: 480 | G25: Bank Transfer | H25: PestAway Services

Sheet Analysis
B1: APARTMENT MANAGEMENT & FINANCIAL ANALYSIS
B6: Property Performance & Operational Report
B8: PROPERTY OVERVIEW | F8: RENT PERFORMANCE | J8: FINANCIAL SUMMARY
B9: Total Apartments | D9: =COUNTA(Table1[Apartment_ID]) -> 16 | F9: Total Rent Due | H9: =SUM(Table3[Due_Amount]) -> 62200 | J9: Rental Income | L9: =H10 -> 60650
B10: Occupied Apartments | D10: =COUNTIF(Table1[Occupancy_Status],"Occupied") -> 12 | F10: Rent Collected | H10: =SUM(Table3[Paid_Amount]) -> 60650 | J10: Operating Expenses | L10: =SUM(Table5[Amount]) -> 20675
B11: Vacant Apartments | D11: =COUNTIF(Table1[Occupancy_Status],"Vacant") -> 4 | F11: Outstanding Balance | H11: =SUM(Table3[Balance]) -> 1550 | J11: Maintenance Cost | L11: =SUM(Table4[Cost]) -> 3455
B12: Occupancy Rate | D12: =D10/D9 -> 0.75 | F12: Collection Rate | H12: =H10/H9 -> 0.97508039 | J12: Total Costs | L12: =L10+L11 -> 24130
B13: Potential Monthly Rent | D13: =SUM(Table1[Monthly_Rent]) -> 41900 | F13: Late Payments | H13: =COUNTIF(Table3[Payment_Timing],"Late") -> 8 | J13: Net Operating Result | L13: =L9-L12 -> 36520
B17: MONTHLY FINANCIAL PERFORMANCE
C19: Month | D19: Rent Due | E19: Rent Collected | F19: Outstanding | G19: Operating Expenses | H19: Maintenance Cost | I19: Total Costs | J19: Net Result
C20: 46174 | D20: N/A | E20: N/A | F20: N/A | G20: =SUMIFS(Table5[Amount],Table5[Expense_Date],">="&Analysis!C20,Table5[Expense_Date],"<"&EDATE(Analysis!C20,1)) -> 5340 | H20: =SUMIFS(Table4[Cost],Table4[Request_Date],">="&Analysis!C20,Table4[Request_Date],"<"&EDATE(Analysis!C20,1)) -> 1040 | I20: =G20+H20 -> 6380 | J20: N/A
C21: 46204 | D21: =SUMIFS(Table3[Due_Amount],Table3[Payment_Month],Analysis!C21) -> 29850 | E21: =SUMIFS(Table3[Paid_Amount],Table3[Payment_Month],Analysis!C21) -> 29200 | F21: =SUMIFS(Table3[Balance],Table3[Payment_Month],Analysis!C21) -> 650 | G21: =SUMIFS(Table5[Amount],Table5[Expense_Date],">="&Analysis!C21,Table5[Expense_Date],"<"&EDATE(Analysis!C21,1)) -> 5900 | H21: =SUMIFS(Table4[Cost],Table4[Request_Date],">="&Analysis!C21,Table4[Request_Date],"<"&EDATE(Analysis!C21,1)) -> 790 | I21: =G21+H21 -> 6690 | J21: =E21-I21 -> 22510
C22: 46235 | D22: =SUMIFS(Table3[Due_Amount],Table3[Payment_Month],Analysis!C22) -> 32350 | E22: =SUMIFS(Table3[Paid_Amount],Table3[Payment_Month],Analysis!C22) -> 31450 | F22: =SUMIFS(Table3[Balance],Table3[Payment_Month],Analysis!C22) -> 900 | G22: =SUMIFS(Table5[Amount],Table5[Expense_Date],">="&Analysis!C22,Table5[Expense_Date],"<"&EDATE(Analysis!C22,1)) -> 9435 | H22: =SUMIFS(Table4[Cost],Table4[Request_Date],">="&Analysis!C22,Table4[Request_Date],"<"&EDATE(Analysis!C22,1)) -> 1625 | I22: =G22+H22 -> 11060 | J22: =E22-I22 -> 20390
B25: MAINTENANCE PERFORMANCE | H25: MANAGEMENT ATTENTION
C26: Open Requests | E26: =COUNTIF(Table4[Maintenance_Status],"<>Completed") -> 6 | I26: Outstanding Rent | K26: =H11 -> 1550
C27: Urgent Requests | E27: =COUNTIF(Table4[Attention_Flag],"Urgent") -> 1 | I27: Urgent Maintenance | K27: =E27 -> 1
C28: Avg Resolution Days | E28: =AVERAGEIF(Table4[Maintenance_Status],"Completed",Table4[Days_Open]) -> 1.0833333 | I28: Vacant Units | K28: =D11 -> 4

Sheet Dashboard
A1: APARTMENT MANAGEMENT | B1: APARTMENT MANAGEMENT DASHBOARD
C2: Executive Property Performance Overview | AA2: Expense Category | AB2: Amount | AD2: Maintenance Status | AE2: Requests | AH2: QUICK INSIGHTS
A3: Dashboard | AA3: Other | AB3: =SUM(AB8:AB12) -> 3655 | AD3: Completed | AE3: =COUNTIF(Table4[Maintenance_Status],Dashboard!AD3) -> 12 | AH3: ="Rent collected increased "&TEXT((Analysis!E22-Analysis!E21)/Analysis!E21,"0.0%")&" vs Jul-26" -> Rent collected increased 7.7% vs Jul-26
D4: OCCUPANCY RATE | H4: RENT COLLECTED | L4: OUTSTANDING RENT | P4: NET OPERATING RESULT | AA4: Utilities | AB4: =SUMIF(Table5[Expense_Category],Dashboard!AA4,Table5[Amount]) -> 7710 | AD4: In Progress | AE4: =COUNTIF(Table4[Maintenance_Status],Dashboard!AD4) -> 3 | AH4: ="Outstanding rent increased "&TEXT((Analysis!F22-Analysis!F21)/Analysis!F21,"0.0%")&" vs Jul-26" -> Outstanding rent increased 38.5% vs Jul-26
A5: Analysis | D5: =Analysis!D12 -> 0.75 | H5: =Analysis!H10 -> 60650 | L5: =Analysis!K26 -> 1550 | P5: =Analysis!L13 -> 36520 | AA5: Cleaning | AB5: =SUMIF(Table5[Expense_Category],Dashboard!AA5,Table5[Amount]) -> 2610 | AD5: Pending | AE5: =COUNTIF(Table4[Maintenance_Status],Dashboard!AD5) -> 3 | AH5: ="Net operating result decreased "&TEXT(ABS((Analysis!J22-Analysis!J21)/Analysis!J21),"0.0%")&" vs Jul-26" -> Net operating result decreased 9.4% vs Jul-26
D6: =Analysis!D10&" of " &Analysis!D9&" units occupied" -> 12 of 16 units occupied | H6: ="▲"&TEXT((Analysis!E22-Analysis!E21)/Analysis!E21,"0.0%")&" vs Jul-26" -> ▲7.7% vs Jul-26 | L6: ="▲ "&TEXT((Analysis!F22-Analysis!F21)/Analysis!F21,"0.0%")&" vs Jul-26" -> ▲ 38.5% vs Jul-26 | P6: ="▼ "&TEXT((Analysis!J22-Analysis!J21)/Analysis!J21,"0.0%")&" vs Jul-26" -> ▼ -9.4% vs Jul-26 | AA6: Security | AB6: =SUMIF(Table5[Expense_Category],Dashboard!AA6,Table5[Amount]) -> 4500 | AH6: =Analysis!D11&" vacant units" -> 4 vacant units
A7: Apartments | AA7: Insurance | AB7: =SUMIF(Table5[Expense_Category],Dashboard!AA7,Table5[Amount]) -> 2200 | AH7: =Analysis!K27&" urgent maintenance request" -> 1 urgent maintenance request
AA8: Internet | AB8: =SUMIF(Table5[Expense_Category],Dashboard!AA8,Table5[Amount]) -> 1800
A9: Tenants | AA9: Supplies | AB9: =SUMIF(Table5[Expense_Category],Dashboard!AA9,Table5[Amount]) -> 525
AA10: Administration | AB10: =SUMIF(Table5[Expense_Category],Dashboard!AA10,Table5[Amount]) -> 350
A11: Rent Payments | AA11: Landscaping | AB11: =SUMIF(Table5[Expense_Category],Dashboard!AA11,Table5[Amount]) -> 500
AA12: Pest Control | AB12: =SUMIF(Table5[Expense_Category],Dashboard!AA12,Table5[Amount]) -> 480
A13: Maintenance | AA13: Building | AB13: Occupied | AC13: Vacant | AD13: Building | AE13: Occupied % | AF13: Vacant %
AA14: Building A | AB14: =COUNTIFS(Table1[Building],Dashboard!AA14,Table1[Occupancy_Status],"Occupied") -> 6 | AC14: =COUNTIFS(Table1[Building],Dashboard!AA14,Table1[Occupancy_Status],"Vacant") -> 3 | AD14: Building A | AE14: =AB14/(AB14+AC14) -> 0.66666667 | AF14: =AC14/(AB14+AC14) -> 0.33333333
A15: Expenses | AA15: Building B | AB15: =COUNTIFS(Table1[Building],Dashboard!AA15,Table1[Occupancy_Status],"Occupied") -> 6 | AC15: =COUNTIFS(Table1[Building],Dashboard!AA15,Table1[Occupancy_Status],"Vacant") -> 1 | AD15: Building B | AE15: =AB15/(AB15+AC15) -> 0.85714286 | AF15: =AC15/(AB15+AC15) -> 0.14285714
AA16: Month | AB16: Rent Collected | AC16: Total Costs | AD16: Net Result
AA17: 46174 | AB17: =NA() -> #N/A | AC17: =Analysis!I20 -> 6380 | AD17: =NA() -> #N/A
AA18: 46204 | AB18: =Analysis!E21 -> 29200 | AC18: =Analysis!I21 -> 6690 | AD18: =Analysis!J21 -> 22510
AA19: 46235 | AB19: =Analysis!E22 -> 31450 | AC19: =Analysis!I22 -> 11060 | AD19: =Analysis!J22 -> 20390
N25: Quick Insights
N28: =AH3 -> Rent collected increased 7.7% vs Jul-26
N31: =AH4 -> Outstanding rent increased 38.5% vs Jul-26
N34: =AH5 -> Net operating result decreased 9.4% vs Jul-26
N37: =AH6 -> 4 vacant units
N40: =AH7 -> 1 urgent maintenance request
